odoo/addons/base_substate/README.rst
odoo/addons/base_substate/__init__.py
odoo/addons/base_substate/__manifest__.py
odoo/addons/base_substate/i18n/base_substate.pot
odoo/addons/base_substate/i18n/es.po
odoo/addons/base_substate/i18n/it.po
odoo/addons/base_substate/i18n/nl.po
odoo/addons/base_substate/models/__init__.py
odoo/addons/base_substate/models/base_substate.py
odoo/addons/base_substate/models/base_substate_mixin.py
odoo/addons/base_substate/readme/CONTRIBUTORS.md
odoo/addons/base_substate/readme/DESCRIPTION.md
odoo/addons/base_substate/readme/USAGE.md
odoo/addons/base_substate/security/base_substate_security.xml
odoo/addons/base_substate/security/ir.model.access.csv
odoo/addons/base_substate/static/description/icon.png
odoo/addons/base_substate/static/description/index.html
odoo/addons/base_substate/tests/__init__.py
odoo/addons/base_substate/tests/common.py
odoo/addons/base_substate/tests/sale_test.py
odoo/addons/base_substate/tests/test_base_substate.py
odoo/addons/base_substate/views/base_substate_type_views.xml
odoo/addons/base_substate/views/base_substate_value_views.xml
odoo/addons/base_substate/views/base_substate_views.xml
odoo_addon_base_substate-19.0.1.0.0.4.dist-info/METADATA
odoo_addon_base_substate-19.0.1.0.0.4.dist-info/WHEEL
odoo_addon_base_substate-19.0.1.0.0.4.dist-info/top_level.txt
odoo_addon_base_substate-19.0.1.0.0.4.dist-info/RECORD
